nonebot_plugin_parser/__init__.py
nonebot_plugin_parser/config.py
nonebot_plugin_parser/constants.py
nonebot_plugin_parser/download/__init__.py
nonebot_plugin_parser/download/task.py
nonebot_plugin_parser/download/ytdlp.py
nonebot_plugin_parser/exception.py
nonebot_plugin_parser/helper.py
nonebot_plugin_parser/matchers/__init__.py
nonebot_plugin_parser/matchers/filter.py
nonebot_plugin_parser/matchers/rule.py
nonebot_plugin_parser/parsers/__init__.py
nonebot_plugin_parser/parsers/acfun/__init__.py
nonebot_plugin_parser/parsers/acfun/video.py
nonebot_plugin_parser/parsers/base.py
nonebot_plugin_parser/parsers/bilibili/__init__.py
nonebot_plugin_parser/parsers/bilibili/article.py
nonebot_plugin_parser/parsers/bilibili/common.py
nonebot_plugin_parser/parsers/bilibili/dynamic.py
nonebot_plugin_parser/parsers/bilibili/favlist.py
nonebot_plugin_parser/parsers/bilibili/live.py
nonebot_plugin_parser/parsers/bilibili/opus.py
nonebot_plugin_parser/parsers/bilibili/video.py
nonebot_plugin_parser/parsers/cookie.py
nonebot_plugin_parser/parsers/data.py
nonebot_plugin_parser/parsers/douyin/__init__.py
nonebot_plugin_parser/parsers/douyin/slides.py
nonebot_plugin_parser/parsers/douyin/video.py
nonebot_plugin_parser/parsers/kuaishou/__init__.py
nonebot_plugin_parser/parsers/kuaishou/states.py
nonebot_plugin_parser/parsers/nga.py
nonebot_plugin_parser/parsers/tiktok.py
nonebot_plugin_parser/parsers/twitter.py
nonebot_plugin_parser/parsers/weibo/__init__.py
nonebot_plugin_parser/parsers/weibo/article.py
nonebot_plugin_parser/parsers/weibo/common.py
nonebot_plugin_parser/parsers/weibo/show.py
nonebot_plugin_parser/parsers/xiaohongshu/__init__.py
nonebot_plugin_parser/parsers/xiaohongshu/common.py
nonebot_plugin_parser/parsers/xiaohongshu/discovery.py
nonebot_plugin_parser/parsers/xiaohongshu/explore.py
nonebot_plugin_parser/parsers/youtube/__init__.py
nonebot_plugin_parser/parsers/youtube/meta.py
nonebot_plugin_parser/renders/__init__.py
nonebot_plugin_parser/renders/base.py
nonebot_plugin_parser-2.3.9.dist-info/WHEEL
nonebot_plugin_parser-2.3.9.dist-info/METADATA
nonebot_plugin_parser-2.3.9.dist-info/RECORD
