Metadata-Version: 2.3
Name: nonebot-plugin-parser
Version: 2.3.9
Summary: NoneBot2 链接分享解析 Alconna 版, 通用媒体卡片渲染(PIL 实现), 支持 B站/抖音/快手/微博/小红书/youtube/tiktok/twitter/acfun/nga
Keywords: acfun,bilibili,douyin,kuaishou,nga,nonebot,nonebot2,tiktok,twitter,video,weibo,xiaohongshu,youtube
Author: fllesser
Author-email: fllesser <fllessive@gmail.com>
Classifier: Development Status :: 5 - Production/Stable
Classifier: Framework :: AsyncIO
Classifier: License :: OSI Approved :: MIT License
Classifier: Operating System :: OS Independent
Classifier: Programming Language :: Python :: 3
Classifier: Programming Language :: Python :: 3 :: Only
Classifier: Programming Language :: Python :: 3.10
Classifier: Programming Language :: Python :: 3.11
Classifier: Programming Language :: Python :: 3.12
Classifier: Programming Language :: Python :: 3.13
Classifier: Programming Language :: Python :: 3.14
Classifier: Topic :: Communications :: Chat
Classifier: Topic :: Internet :: WWW/HTTP
Classifier: Topic :: Multimedia :: Video
Requires-Dist: nonebot2>=2.4.3,<3.0.0
Requires-Dist: pillow>=11.0.0
Requires-Dist: tqdm>=4.67.1,<5.0.0
Requires-Dist: aiofiles>=25.1.0
Requires-Dist: httpx>=0.27.2,<1.0.0
Requires-Dist: msgspec>=0.20.0,<1.0.0
Requires-Dist: apilmoji[tqdm]>=0.2.4,<1.0.0
Requires-Dist: beautifulsoup4>=4.12.0,<5.0.0
Requires-Dist: curl-cffi>=0.13.0,!=0.14.0,<1.0.0
Requires-Dist: bilibili-api-python>=17.4.1,<18.0.0
Requires-Dist: nonebot-plugin-alconna>=0.59.4,<1.0.0
Requires-Dist: nonebot-plugin-apscheduler>=0.5.0,<1.0.0
Requires-Dist: nonebot-plugin-localstore>=0.7.4,<1.0.0
Requires-Dist: nonebot-plugin-uninfo>=0.10.1,<1.0.0
Requires-Dist: nonebot-plugin-htmlkit>=0.1.0rc4 ; extra == 'all'
Requires-Dist: nonebot-plugin-htmlrender>=0.6.7 ; extra == 'all'
Requires-Dist: yt-dlp[default]>=2026.1.29 ; extra == 'all'
Requires-Dist: emosvg>=0.1.6 ; extra == 'all'
Requires-Dist: emosvg>=0.1.6 ; extra == 'emosvg'
Requires-Dist: nonebot-plugin-htmlkit>=0.1.0rc4 ; extra == 'htmlkit'
Requires-Dist: nonebot-plugin-htmlrender>=0.6.7 ; extra == 'htmlrender'
Requires-Dist: yt-dlp[default]>=2025.1.29 ; extra == 'ytdlp'
Requires-Python: >=3.10
Project-URL: IssueTracker, https://github.com/fllesser/nonebot-plugin-parser/issues
Project-URL: Release, https://github.com/fllesser/nonebot-plugin-parser/releases
Project-URL: Repository, https://github.com/fllesser/nonebot-plugin-parser
Provides-Extra: all
Provides-Extra: emosvg
Provides-Extra: htmlkit
Provides-Extra: htmlrender
Provides-Extra: ytdlp
